smt_portfolio/__init__.py
smt_portfolio-1.0.0.dist-info/METADATA
smt_portfolio-1.0.0.dist-info/WHEEL
smt_portfolio-1.0.0.dist-info/entry_points.txt
smt_portfolio-1.0.0.dist-info/licenses/LICENSE
smt_portfolio-1.0.0.dist-info/RECORD
