Metadata-Version: 2.3
Name: smt-portfolio
Version: 1.0.0
Summary: A simple wrapper to run multiple SMT solvers in parallel.
Project-URL: Homepage, https://github.com/yangky11/smt-portfolio
Project-URL: Bug Tracker, https://github.com/yangky11/smt-portfolio/issues
Author-email: Kaiyu Yang <kaiyuy@caltech.edu>
License: MIT License
License-File: LICENSE
Keywords: SMT
Classifier: License :: OSI Approved :: MIT License
Classifier: Operating System :: MacOS
Classifier: Operating System :: POSIX :: Linux
Classifier: Programming Language :: Python :: 3
Requires-Python: >=3.9
Provides-Extra: all
Requires-Dist: black[jupyter]; extra == 'all'
Requires-Dist: hatch; extra == 'all'
Requires-Dist: ipython; extra == 'all'
Requires-Dist: mypy; extra == 'all'
Requires-Dist: notebook; extra == 'all'
Provides-Extra: dev
Requires-Dist: hatch; extra == 'dev'
Requires-Dist: ipython; extra == 'dev'
Requires-Dist: notebook; extra == 'dev'
Provides-Extra: lint
Requires-Dist: black[jupyter]; extra == 'lint'
Requires-Dist: mypy; extra == 'lint'
